donjon_painter/__init__.py
donjon_painter/imgmap.py
donjon_painter/menu.py
donjon_painter/painter.py
donjon_painter/stretch.py
donjon_painter/test_sample.py
donjon_painter/themes.py
donjon_painter/txtmap.py
donjon_painter/themes/basic/0-Floor.png
donjon_painter/themes/basic/1-Space.png
donjon_painter/themes/basic/10-B_Stair_D.png
donjon_painter/themes/basic/10-L_Stair_D.png
donjon_painter/themes/basic/10-R_Stair_D.png
donjon_painter/themes/basic/10-T_Stair_D.png
donjon_painter/themes/basic/11-B_Stair_DD.png
donjon_painter/themes/basic/11-L_Stair_DD.png
donjon_painter/themes/basic/11-R_Stair_DD.png
donjon_painter/themes/basic/11-T_Stair_DD.png
donjon_painter/themes/basic/2-B_Wall.png
donjon_painter/themes/basic/2-L_Wall.png
donjon_painter/themes/basic/2-R_Wall.png
donjon_painter/themes/basic/2-T_Wall.png
donjon_painter/themes/basic/3-BL_Corner_I.png
donjon_painter/themes/basic/3-BR_Corner_I.png
donjon_painter/themes/basic/3-TL_Corner_I.png
donjon_painter/themes/basic/3-TR_Corner_I.png
donjon_painter/themes/basic/4-BL_Corner_O.png
donjon_painter/themes/basic/4-BR_Corner_O.png
donjon_painter/themes/basic/4-TL_Corner_O.png
donjon_painter/themes/basic/4-TR_Corner_O.png
donjon_painter/themes/basic/5-B_Door.png
donjon_painter/themes/basic/5-L_Door.png
donjon_painter/themes/basic/5-R_Door.png
donjon_painter/themes/basic/5-T_Door.png
donjon_painter/themes/basic/6-B_Door_Secret.png
donjon_painter/themes/basic/6-L_Door_Secret.png
donjon_painter/themes/basic/6-R_Door_Secret.png
donjon_painter/themes/basic/6-T_Door_Secret.png
donjon_painter/themes/basic/7-B_Door_Portcullis.png
donjon_painter/themes/basic/7-L_Door_Portcullis.png
donjon_painter/themes/basic/7-R_Door_Portcullis.png
donjon_painter/themes/basic/7-T_Door_Portcullis.png
donjon_painter/themes/basic/8-B_Stair_U.png
donjon_painter/themes/basic/8-L_Stair_U.png
donjon_painter/themes/basic/8-R_Stair_U.png
donjon_painter/themes/basic/8-T_Stair_U.png
donjon_painter/themes/basic/9-B_Stair_UU.png
donjon_painter-0.9.5.dist-info/LICENSE
donjon_painter-0.9.5.dist-info/METADATA
donjon_painter-0.9.5.dist-info/WHEEL
donjon_painter-0.9.5.dist-info/entry_points.txt
donjon_painter-0.9.5.dist-info/top_level.txt
donjon_painter-0.9.5.dist-info/RECORD
