Metadata-Version: 2.1
Name: donjon-painter
Version: 0.9.5
Summary: Graphical map translator for donjon's Random Dungeon Generator TSV files.
Home-page: https://github.com/donjon-painter/donjon-painter
Author: Korvin Roganov
Author-email: korvinagor@vivaldi.net
License: GPLv3
Platform: UNKNOWN
Classifier: Programming Language :: Python :: 3 :: Only
Classifier: Programming Language :: Python :: 3.5
Classifier: Programming Language :: Python :: 3.6
Classifier: Programming Language :: Python :: 3.7
Classifier: Development Status :: 4 - Beta
Classifier: Environment :: Console
Classifier: Topic :: Utilities
Classifier: License :: OSI Approved :: GNU General Public License v3 or later (GPLv3+)
Classifier: Operating System :: OS Independent
Requires-Python: >=3.5
Requires-Dist: Pillow
